README
setup.py
pypaster/__init__.py
pypaster/pypaster.py
pypaster.egg-info/PKG-INFO
pypaster.egg-info/SOURCES.txt
pypaster.egg-info/dependency_links.txt
pypaster.egg-info/entry_points.txt
pypaster.egg-info/requires.txt
pypaster.egg-info/top_level.txt
pypaster.egg-info/zip-safe