Metadata-Version: 1.1
Name: pypaster
Version: 0.6
Summary: Uploads code snippets to http://pypaste.com
Home-page: https://hg.mattikus.com/pypaster/
Author: Matt Kemp
Author-email: matt@mattikus.com
License: MIT
Keywords: pastebin,pypaste,pypaster
Platform: UNKNOWN
Provides: pypaster
